WebWeaver/__init__.py
WebWeaver/util.py
WebWeaver/webWeaver.py
webweaver-1.2.3.dist-info/licenses/LICENSE.txt
webweaver-1.2.3.dist-info/METADATA
webweaver-1.2.3.dist-info/WHEEL
webweaver-1.2.3.dist-info/top_level.txt
webweaver-1.2.3.dist-info/RECORD
