Metadata-Version: 2.4
Name: WebWeaver
Version: 1.2.3
Summary: A package used for web crawling
Author: Shubakar Poda, Nirmal Babu & Vamsi Krishna Kollipara
Author-email: redblack09062024@gmail.com
License-File: LICENSE.txt
Requires-Dist: requests==2.32.3
Dynamic: author
Dynamic: author-email
Dynamic: description
Dynamic: description-content-type
Dynamic: license-file
Dynamic: requires-dist
Dynamic: summary
